traitgpt/__init__.py
traitgpt/cli.py
traitgpt/prompts.py
traitgpt/traitgpt.py
traitgpt-0.0.10.dist-info/LICENSE
traitgpt-0.0.10.dist-info/METADATA
traitgpt-0.0.10.dist-info/WHEEL
traitgpt-0.0.10.dist-info/entry_points.txt
traitgpt-0.0.10.dist-info/RECORD
